{
  "version": "6",
  "dialect": "sqlite",
  "id": "1a69d532-b3a4-4c3d-ad20-d3560231ae08",
  "prevId": "e4ef3000-e125-42aa-9770-6c556764f86e",
  "tables": {
    "tasks": {
      "name": "tasks",
      "columns": {
        "id": {
          "name": "id",
          "type": "integer",
          "primaryKey": true,
          "notNull": true,
          "autoincrement": true
        },
        "name": {
          "name": "name",
          "type": "text",
          "primaryKey": false,
          "notNull": true,
          "autoincrement": false
        },
        "done": {
          "name": "done",
          "type": "integer",
          "primaryKey": false,
          "notNull": true,
          "autoincrement": false,
          "default": false
        },
        "updated_at": {
          "name": "updated_at",
          "type": "integer",
          "primaryKey": false,
          "notNull": false,
          "autoincrement": false
        }
      },
      "indexes": {},
      "foreignKeys": {},
      "compositePrimaryKeys": {},
      "uniqueConstraints": {},
      "checkConstraints": {}
    }
  },
  "views": {},
  "enums": {},
  "_meta": {
    "schemas": {},
    "tables": {
      "\"users\"": "\"tasks\""
    },
    "columns": {}
  },
  "internal": {
    "indexes": {}
  }
}